maa/__init__.py
maa/agent_client.py
maa/buffer.py
maa/context.py
maa/controller.py
maa/custom_action.py
maa/custom_recognition.py
maa/define.py
maa/event_sink.py
maa/job.py
maa/library.py
maa/pipeline.py
maa/resource.py
maa/tasker.py
maa/toolkit.py
maa/agent/__init__.py
maa/agent/agent_server.py
maa/bin/DirectML.dll
maa/bin/MaaAdbControlUnit.dll
maa/bin/MaaAgentClient.dll
maa/bin/MaaAgentServer.dll
maa/bin/MaaCustomControlUnit.dll
maa/bin/MaaFramework.dll
maa/bin/MaaToolkit.dll
maa/bin/MaaUtils.dll
maa/bin/MaaWin32ControlUnit.dll
maa/bin/fastdeploy_ppocr_maa.dll
maa/bin/onnxruntime_maa.dll
maa/bin/opencv_world4_maa.dll
maa/bin/plugins/MaaPluginDemo.dll
maafw-5.3.0.dist-info/licenses/LICENSE.md
maafw-5.3.0.dist-info/METADATA
maafw-5.3.0.dist-info/WHEEL
maafw-5.3.0.dist-info/RECORD
