Metadata-Version: 2.4
Name: MaaFw
Version: 5.3.0
Summary: An automation black-box testing framework based on image recognition
Project-URL: Homepage, https://github.com/MaaXYZ/MaaFramework
Author: MaaXYZ
License-File: LICENSE.md
Requires-Python: >=3.9
Requires-Dist: maaagentbinary
Requires-Dist: numpy
Requires-Dist: strenum
